README.md
setup.py
LebesgueUtility.egg-info/PKG-INFO
LebesgueUtility.egg-info/SOURCES.txt
LebesgueUtility.egg-info/dependency_links.txt
LebesgueUtility.egg-info/entry_points.txt
LebesgueUtility.egg-info/requires.txt
LebesgueUtility.egg-info/top_level.txt
lebesgue_sdk/__init__.py
lebesgue_sdk/cmd.py
lebesgue_sdk/lebesgue_sdk.py