Metadata-Version: 1.2
Name: LebesgueUtility
Version: 0.3.2
Summary: Lebesgue Utility
Home-page: http://lebesgue.dp.tech/#/
Author: DP Technology
Author-email: baixk@dp.tech
License: UNKNOWN
Platform: UNKNOWN
Requires-Python: >=3.6
